benchclients/__init__.py
benchclients/_version.py
benchclients/base.py
benchclients/conbench.py
benchclients/http.py
benchclients/logging.py
benchclients-2024.3.29.1.dist-info/METADATA
benchclients-2024.3.29.1.dist-info/WHEEL
benchclients-2024.3.29.1.dist-info/top_level.txt
benchclients-2024.3.29.1.dist-info/RECORD
