Metadata-Version: 2.1
Name: benchclients
Version: 2024.3.29.1
Summary: Clients for the Conbench ecosystem
Home-page: https://github.com/conbench/conbench/tree/main/benchclients
Maintainer: Voltron Data
Maintainer-email: conbench@voltrondata.com
Classifier: Programming Language :: Python :: 3.8
Classifier: License :: OSI Approved :: Apache Software License
Requires-Python: >=3.8
Requires-Dist: requests
Requires-Dist: urllib3
Provides-Extra: dev
Requires-Dist: pytest ; extra == 'dev'
Requires-Dist: pytest-httpserver ; extra == 'dev'
